{
    "type": "FeatureCollection",
    "features": [
        {
            "type": "Feature",
            "properties": {
                "ICAO": "BIRD",
                "Type": "FIR",
                "Name": "Reykjavik Oceanic",
                "Upper": "UNL",
                "Lower": "GND",
                "Unit": [{
                    "Name": "OACC Reykjavik",
                    "Callsign": "Reykjavík Control"
                }]
            },
            "geometry": {
                "type": "Polygon",
                "coordinates": [
                    [
                        [0.0000, 61.0000],
                        [0.0000, 82.0000],
                        [30.0000, 82.0000],
                        [0.0000, 90.0000],
                        [-60.0000, 82.0000],
                        [-75.0000, 78.0000],
                        [-76.0000, 76.0000],
                        [-57.7500, 65.0000],
                        [-55.6667, 63.5000],
                        [-39.0000, 63.5000],
                        [-30.0000, 61.0000],
                        [0.0000, 61.0000]
                    ]
                ]
            }
        },
        {
            "type": "Feature",
            "properties": {
                "ICAO": "BIRD",
                "Type": "FIR",
                "Name": "Reykjavik FIR",
                "Upper": "UNL",
                "Lower": "GND",
                "Unit": [{
                    "Name": "OACC Reykjavik",
                    "Callsign": "Reykjavík Control"
                }]
            },
            "geometry": {
                "type": "Polygon",
                "coordinates": [
                    [
                        [-20.0000, 73.0000],
                        [-20.0000, 70.0000],
                        [-39.0000, 63.5000],
                        [-30.0000, 61.0000],
                        [0.0000, 61.0000],
                        [0.0000, 73.0000],
                        [-20.0000, 73.0000]
                    ]
                ]
            }
        }        
    ]
}
